README.md
setup.py
faa_tpp/__init__.py
faa_tpp.egg-info/PKG-INFO
faa_tpp.egg-info/SOURCES.txt
faa_tpp.egg-info/dependency_links.txt
faa_tpp.egg-info/top_level.txt