Metadata-Version: 1.0
Name: faa-tpp
Version: 0.1
Summary: Get FAA dTPP data
Home-page: https://github.com/jgillmanjr/faa_tpp
Author: Jason Gillman Jr.
Author-email: jason@rrfaae.com
License: UNKNOWN
Platform: UNKNOWN
